film_review_explorer/__init__.py
film_review_explorer/dataframe_preprocessor.py
film_review_explorer/topic_modeler.py
film_review_explorer-1.0.dist-info/LICENSE
film_review_explorer-1.0.dist-info/METADATA
film_review_explorer-1.0.dist-info/WHEEL
film_review_explorer-1.0.dist-info/top_level.txt
film_review_explorer-1.0.dist-info/RECORD
