Metadata-Version: 2.1
Name: film-review-explorer
Version: 1.0
Summary: A python package for exploring film reviews.
Author-email: Chang Jianghan <jianghanchang@hotmail.com>
License: MIT License
Project-URL: Repository, https://github.com/pip-chang/film_review_explorer
Keywords: film
Classifier: Programming Language :: Python :: 3
Classifier: License :: OSI Approved :: MIT License
Classifier: Operating System :: OS Independent
Requires-Python: >=3.7
License-File: LICENSE
Requires-Dist: spacy (>=3.5.0)
Requires-Dist: pandas (>=2.0.1)
Requires-Dist: pytest (>=7.2.1)
Requires-Dist: seaborn (>=0.12.2)
Requires-Dist: myst-parser (>=0.18.1)
